{"name": "کالیفرنیا", "id": 115934, "predecessors": [{"name": "ایالت‌های_ایالات_متحده_آمریکا", "id": 1268783}, {"name": "اقیانوس_آرام", "id": 139973}], "successors": [{"name": "دانشگاه‌ها_و_کالج‌ها_در_کالیفرنیا", "id": 99871}, {"name": "پارک‌های_ملی_در_کالیفرنیا", "id": 168294}, {"name": "اهالی_کالیفرنیا", "id": 176471}, {"name": "شهرهای_کالیفرنیا", "id": 186556}, {"name": "شهرستان‌های_کالیفرنیا", "id": 222540}, {"name": "فرهنگ_کالیفرنیا", "id": 903345}, {"name": "شرکت‌های_کالیفرنیا", "id": 1676784}, {"name": "حوزه‌های_انتخابیه_کالیفرنیا", "id": 1852433}, {"name": "فعالان_اهل_کالیفرنیا", "id": 3654079}, {"name": "مرکز_شهرستان‌های_کالیفرنیا", "id": 1357779}, {"name": "کوه‌های_پارک_ملی_یوسیمیتی", "id": 1815656}, {"name": "کوه‌های_شمال_کالیفرنیا", "id": 3621686}, {"name": "دریاچه_تاهو", "id": 1316959}, {"name": "بیابان_موهاوی", "id": 649306}, {"name": "سیلیکون_ولی", "id": 812376}, {"name": "سیرا_نوادا", "id": 1250111}, {"name": "جنوب_کالیفرنیا", "id": 1250140}, {"name": "دره_مرکزی", "id": 1316939}, {"name": "سن‌واکین_ولی", "id": 3616284}, {"name": "دره_سن_فرناندو", "id": 1101973}, {"name": "پارک_ملی_دث_ولی", "id": 649206}, {"name": "مناطق_مسکونی_ساحلی_کالیفرنیا", "id": 1058703}, {"name": "مناطق_سرشماری‌شده_در_کالیفرنیا", "id": 1799219}, {"name": "شهرک‌های_شرکتی_در_کالیفرنیا", "id": 2296522}, {"name": "مناطق_مسکونی_پیشین_در_کالیفرنیا", "id": 2426976}, {"name": "سکونتگاه‌های_ثبت‌نشده_در_کالیفرنیا", "id": 2461840}, {"name": "مناطق_مسکونی_در_سیرا_نوادا", "id": 3888997}, {"name": "مناطق_مسکونی_در_رود_ساکرامنتو", "id": 3889031}, {"name": "منطقه_کلان‌شهری_ساکرامنتو", "id": 3267613}, {"name": "بناهای_شاخص_در_لس‌آنجلس", "id": 1404221}, {"name": "بناهای_شاخص_در_سان‌فرانسیسکو", "id": 1404241}, {"name": "مناطق_مسکونی_خالی_از_سکنه_در_کالیفرنیا", "id": 2300108}, {"name": "بناهای_شاخص_تاریخی_کالیفرنیا", "id": 4695506}, {"name": "ورزشگاه‌های_کالیفرنیا", "id": 439270}, {"name": "ورزشکاران_اهل_کالیفرنیا", "id": 1148993}, {"name": "علم_و_فناوری_در_منطقه_خلیج_سان‌فرانسیسکو", "id": 2296900}, {"name": "دانشمندان_اهل_کالیفرنیا", "id": 4837349}, {"name": "علم_و_فناوری_در_منطقه_لس_آنجلس_بزرگ", "id": 5011209}, {"name": "شرکت‌های_فناوری_کالیفرنیا", "id": 5026559}, {"name": "مهندسان_اهل_کالیفرنیا", "id": 5848662}, {"name": "پایگاه‌های_نظامی_در_کالیفرنیا", "id": 1084240}, {"name": "کشتی‌های_نیروی_دریایی_ایالات_متحده_آمریکا_با_نام‌های_مربوط_به_کالیفرنیا", "id": 3983250}, {"name": "فرودگاه‌های_کالیفرنیا", "id": 236042}, {"name": "هوانوردان_اهل_کالیفرنیا", "id": 5057576}, {"name": "سازمان‌های_ناسودبر_در_کالیفرنیا", "id": 1635624}, {"name": "تالارهای_مشاهیر_در_کالیفرنیا", "id": 1813436}, {"name": "آموزگاران_اهل_کالیفرنیا", "id": 4709474}, {"name": "مناطق_سرشماری‌شده_در_شهرستان_اینیو،_کالیفرنیا", "id": 4497654}, {"name": "سکونتگاه‌های_ثبت‌نشده_در_شهرستان_اینیو،_کالیفرنیا", "id": 4654821}, {"name": "مناطق_سرشماری‌شده_در_شهرستان_سانتا_کروز،_کالیفرنیا", "id": 4497742}, {"name": "مناطق_سرشماری‌شده_در_شهرستان_کرن،_کالیفرنیا", "id": 4497873}, {"name": "سکونتگاه‌های_ثبت‌نشده_در_شهرستان_کرن،_کالیفرنیا", "id": 4654791}, {"name": "سکونتگاه‌های_ثبت‌نشده_در_شهرستان_مونتری،_کالیفرنیا", "id": 4705703}, {"name": "مناطق_سرشماری‌شده_در_شهرستان_هامبولت،_کالیفرنیا", "id": 4499449}, {"name": "اهالی_کارمل-بای-د-سی،_کالیفرنیا", "id": 3887444}, {"name": "محله‌ها_در_لس_آنجلس", "id": 1223605}, {"name": "محله‌ها_در_سن_دیگو", "id": 1668734}, {"name": "اهالی_منطقه_خلیج_سان‌فرانسیسکو", "id": 1170773}, {"name": "مناطق_سرشماری‌شده_در_شهرستان_استانیسلاس،_کالیفرنیا", "id": 4497571}, {"name": "سکونتگاه‌های_ثبت‌نشده_در_شهرستان_ال_دورادو،_کالیفرنیا", "id": 4654477}, {"name": "سکونتگاه‌های_ثبت_نشده_در_شهرستان_آمادور،_کالیفرنیا", "id": 4506418}, {"name": "سکونتگاه‌های_ثبت‌نشده_در_شهرستان_پلاسر،_کالیفرنیا", "id": 4705709}, {"name": "مناطق_سرشماری‌شده_در_شهرستان_پلوماس،_کالیفرنیا", "id": 4497583}, {"name": "مناطق_سرشماری‌شده_در_شهرستان_ساکرامنتو،_کالیفرنیا", "id": 4497816}, {"name": "اهالی_ساکرامنتو،_کالیفرنیا", "id": 1136288}, {"name": "مناطق_سرشماری‌شده_در_شهرستان_سن‌واکین،_کالیفرنیا", "id": 4497817}, {"name": "سکونتگاه‌های_ثبت_نشده_در_شهرستان_کالاوراس،_کالیفرنیا", "id": 4506570}, {"name": "سکونتگاه‌های_ثبت‌نشده_در_شهرستان_کینگز،_کالیفرنیا", "id": 4654842}, {"name": "مناطق_سرشماری‌شده_در_شهرستان_مرسد،_کالیفرنیا", "id": 4498045}, {"name": "جاذبه‌های_گردشگری_دره_سیلیکون", "id": 1094700}, {"name": "فرودگاه‌های_منطقه_خلیج_سان‌فرانسیسکو", "id": 1140451}, {"name": "شرکت‌های_سان‌فرانسیسکو،_کالیفرنیا", "id": 2047657}, {"name": "ورزشکاران_اهل_منطقه_خلیج_سان‌فرانسیسکو", "id": 4602001}, {"name": "ورزشکاران_کشتی_حرفه‌ای_اهل_کالیفرنیا", "id": 5591652}, {"name": "نمایندگان_کنگره_آمریکا_از_ایالت_کالیفرنیا", "id": 321888}, {"name": "جمهوری‌خواهان_اهل_کالیفرنیا", "id": 436445}, {"name": "زنان_سیاستمدار_در_کالیفرنیا", "id": 2294351}, {"name": "کسکیدز", "id": 1320388}, {"name": "تاریخ_طبیعی_دره_مرکزی_(کالیفرنیا)", "id": 4277359}, {"name": "تاریخ_طبیعی_بیابان_موهاوی", "id": 4277362}, {"name": "تاریخ_طبیعی_جزایر_چنل_(کالیفرنیا)", "id": 4277371}, {"name": "تاریخ_طبیعی_رشته‌کوه‌های_پنینسولار", "id": 4277380}, {"name": "تاریخ_طبیعی_کوهستان‌های_سانتا_مونیکا", "id": 4277381}, {"name": "تاریخ_طبیعی_رشته‌کوه‌های_ترنسورس", "id": 4277383}, {"name": "تاریخ_طبیعی_رشته‌کوه‌های_ساحلی_کالیفرنیا", "id": 4277407}, {"name": "تاریخ_طبیعی_منطقه_خلیج_سان‌فرانسیسکو", "id": 5099589}, {"name": "زیاگان_گریت_بیسین", "id": 3979824}, {"name": "گیاگان_گریت_بیسین", "id": 4517654}, {"name": "جنگل_ملی_اینیو", "id": 2090716}, {"name": "انجمن‌های_معدنچیان_تب_طلا_در_کالیفرنیا", "id": 4422579}, {"name": "شهرهای_منطقه_شهری_ساکرامنتو", "id": 3398229}, {"name": "فرمانداران_ایالت_کالیفرنیا", "id": 3067411}, {"name": "شرکت‌های_بهداشت_و_درمان_کالیفرنیا", "id": 4492323}, {"name": "وکیلان_اهل_کالیفرنیا", "id": 4647756}, {"name": "مرگ‌ها_به_وسیله_اسلحه_گرم_در_کالیفرنیا", "id": 1508634}, {"name": "بازیگران_زن_اهل_کالیفرنیا", "id": 1668847}, {"name": "مدل‌های_زن_اهل_کالیفرنیا", "id": 4052665}, {"name": "درگذشتگان_به_علت_سرطان_در_کالیفرنیا", "id": 964790}, {"name": "درگذشتگان_به_علت_بیماری_در_کالیفرنیا", "id": 1508637}, {"name": "مرگ‌های_ناشی_از_موادمخدر_در_کالیفرنیا", "id": 1508638}, {"name": "خودکشی‌ها_در_کالیفرنیا", "id": 1550727}, {"name": "درگذشتگان_در_سوانح_در_کالیفرنیا", "id": 1807765}, {"name": "افراد_کشته‌شده_در_کالیفرنیا", "id": 1071234}, {"name": "محکومان_به_جرم_قتل_توسط_کالیفرنیا", "id": 4652110}, {"name": "کشتگان_در_لس_آنجلس", "id": 4652937}, {"name": "شهرداران_در_کالیفرنیا", "id": 2296287}, {"name": "سیاستمداران_اهل_لس_آنجلس", "id": 4679991}, {"name": "دانش‌آموختگان_دانشگاه_ایالتی_کالیفرنیا_در_فولرتون", "id": 4318650}, {"name": "شرکت‌های_سانتا_کلارا،_کالیفرنیا", "id": 1914739}, {"name": "شرکت‌های_سن‌خوزه،_کالیفرنیا", "id": 1914929}, {"name": "راه‌یافتگان_به_تالار_مشاهیر_جایزه_ویل_آیزنر", "id": 3542073}, {"name": "شرکت‌های_سن_دیگو", "id": 4553111}, {"name": "گروه‌های_موسیقی_لس_آنجلس،_کالیفرنیا", "id": 888379}, {"name": "شرکت‌های_لس_آنجلس_(کالیفرنیا)", "id": 1494643}, {"name": "دانشگاه‌ها_در_شهرستان_لس_آنجلس،_کالیفرنیا", "id": 1550501}, {"name": "شرکت‌های_ارواین،_کالیفرنیا", "id": 1992058}, {"name": "شرکت‌های_منلو_پارک،_کالیفرنیا", "id": 884015}, {"name": "شرکت‌های_بورلی‌هیلز،_کالیفرنیا", "id": 1520909}, {"name": "شرکت‌ها_در_سان_ماتیو،_کالیفرنیا", "id": 3224657}, {"name": "شرکت‌ها_در_کال‌ور_سیتی،_کالیفرنیا", "id": 3224718}, {"name": "شرکت‌ها_در_پالو_آلتو،_کالیفرنیا", "id": 3224721}, {"name": "شرکت‌های_سنتا_مونیکا،_کالیفرنیا", "id": 3691545}, {"name": "شرکت‌های_بربنک،_کالیفرنیا", "id": 3699809}, {"name": "شرکت‌های_سانی_ویل،_کالیفرنیا", "id": 4553156}, {"name": "اعضای_انجمن_فیلم‌برداران_آمریکا", "id": 5182996}]}