{"name": "فیلم‌های_علمی_تخیلی_دهه_۲۰۱۰_(میلادی)", "id": 1182826, "predecessors": [{"name": "فیلم_در_دهه_۲۰۱۰_(میلادی)", "id": 750253}], "successors": [{"name": "فیلم‌های_ترسناک_تخیلی_دهه_۲۰۱۰_(میلادی)", "id": 4566707}, {"name": "فیلم‌های_علمی_تخیلی_کمدی_دهه_۲۰۱۰_(میلادی)", "id": 4566846}, {"name": "فیلم‌های_اکشن_علمی_تخیلی_دهه_۲۰۱۰_(میلادی)", "id": 5112057}, {"name": "فیلم‌های_اکشن_علمی_تخیلی_۲۰۱۸_(میلادی)", "id": 6323532}, {"name": "فیلم‌های_اکشن_علمی_تخیلی_۲۰۱۷_(میلادی)", "id": 6295266}, {"name": "فیلم‌های_اکشن_علمی_تخیلی_۲۰۱۶_(میلادی)", "id": 6290381}, {"name": "فیلم‌های_اکشن_علمی_تخیلی_۲۰۱۵_(میلادی)", "id": 6288006}, {"name": "فیلم‌های_اکشن_علمی_تخیلی_۲۰۱۴_(میلادی)", "id": 6242360}, {"name": "فیلم‌های_اکشن_علمی_تخیلی_۲۰۱۳_(میلادی)", "id": 6238057}, {"name": "فیلم‌های_اکشن_علمی_تخیلی_۲۰۱۲_(میلادی)", "id": 6235326}]}