{"name": "شهرها_و_روستاهای_کامپانیا", "id": 1225221, "predecessors": [{"name": "منطقه‌های_ایتالیا", "id": 318102}, {"name": "جغرافیای_اروپا", "id": 4571}], "successors": [{"name": "محل‌های_رومی_کامپانیا", "id": 2092790}, {"name": "کومونه‌های_استان_سالرنو", "id": 2848157}, {"name": "کومونه‌های_استان_آولینو", "id": 3585204}, {"name": "کومونه‌های_استان_ناپل", "id": 3713941}, {"name": "اهالی_سالرنو", "id": 905386}, {"name": "اهالی_کازرتا", "id": 3203578}, {"name": "اهالی_ناپل", "id": 515253}, {"name": "اهالی_کاستلاماره_دی_استابیا", "id": 2093584}, {"name": "بازیکنان_باشگاه_آولینو", "id": 3527566}, {"name": "بازیکنان_باشگاه_سالرنیتانا", "id": 3677862}, {"name": "مربیان_باشگاه_فوتبال_سالرنیتانا", "id": 3946500}, {"name": "بازیکنان_باشگاه_بنونتو", "id": 3877330}, {"name": "مربیان_باشگاه_بنونتو", "id": 3877331}]}