{"name": "الگو:جعبه_اطلاعات_ورزشی", "id": 1270567, "predecessors": [{"name": "الگو:جعبه_اطلاعات_هنری_و_فرهنگی", "id": 2438458}, {"name": "الگو:جعبه‌های_اطلاعات", "id": 48802}, {"name": "الگو:ورزش", "id": 178672}, {"name": "الگو:جامعه_و_علوم_اجتماعی", "id": 1769341}], "successors": [{"name": "الگو:جعبه_اطلاعات_ورزشکار", "id": 3219050}, {"name": "الگو:جعبه_اطلاعات_مدال", "id": 3637626}, {"name": "الگو:جعبه‌های_اطلاعات_فوتبال", "id": 507466}, {"name": "جعبه_اطلاعات_بازی‌های_آسیایی", "id": 620938}]}