{"name": "کشتی‌های_بادبانی", "id": 1555407, "predecessors": [{"name": "انواع_قایق‌ها", "id": 1505071}, {"name": "مدیریت_ویکی‌پدیا", "id": 49566}], "successors": [{"name": "بادبان‌بندی", "id": 1555404}, {"name": "کشتی‌های_دو_دکله", "id": 2494973}, {"name": "کلاس‌های_اسلوپ", "id": 2489399}, {"name": "کشتی‌های_خدماتی_کاتر_درآمدی_ایالات_متحده_آمریکا", "id": 5261931}, {"name": "کشتی‌های_سه_دکله", "id": 3442872}, {"name": "کشتی‌های_تجاری_عصر_دریانوردی", "id": 4694721}, {"name": "کشتی‌های_عصر_دریانوردی_ایالات_متحده_آمریکا", "id": 3942662}, {"name": "کشتی‌های_تجاری_عصر_دریانوردی_انگلستان", "id": 4694723}]}