{"name": "ناسا", "id": 155520, "predecessors": [{"name": "آزمایشگاه‌های_ملی_آمریکا", "id": 156481}, {"name": "آژانس‌های_فضایی", "id": 212960}, {"name": "آژانس‌های_مستقل_دولت_ایالات_متحده_آمریکا", "id": 1996327}, {"name": "سازمان‌های_علمی_و_آموزشی_آمریکا", "id": 220354}, {"name": "سازمان‌های_فضایی", "id": 4747146}, {"name": "سازمان‌های_واشینگتن،_دی.سی.", "id": 2077312}, {"name": "تاریخ_شهرهای_ایالات_متحده_آمریکا", "id": 758503}, {"name": "دهه‌ها_(میلادی)", "id": 343732}], "successors": [{"name": "تصاویر_ناسا", "id": 135538}, {"name": "ماموریت‌های_آپولو", "id": 179814}, {"name": "مأموریت‌های_شاتل_فضایی", "id": 632511}, {"name": "کارکنان_ناسا", "id": 1111945}, {"name": "فرود_انسان_بر_روی_ماه", "id": 2035800}, {"name": "برنامه‌های_ناسا", "id": 3271005}, {"name": "هواگردهای_ناسا", "id": 2954493}, {"name": "کاوشگرهای_فضایی_ناسا", "id": 2954498}]}