{"name": "نرم‌افزار_آزاد", "id": 15585, "predecessors": [{"name": "اخلاق_کاربردی", "id": 965272}, {"name": "محتویات_آزاد", "id": 477299}, {"name": "اجازه‌نامه‌های_نرم‌افزار", "id": 432041}, {"name": "نرم‌افزار_آزاد", "id": 15585}], "successors": [{"name": "مرورگرهای_وب_آزاد", "id": 425499}, {"name": "سیستم‌عامل‌های_آزاد", "id": 426215}, {"name": "نرم‌افزارهای_آزاد_چندسکویی", "id": 426680}, {"name": "سامانه‌های_مدیریت_محتوای_آزاد", "id": 428136}, {"name": "نرم‌افزارهای_پروژه_گنو", "id": 430532}, {"name": "پروژه‌های_نرم‌افزار_آزاد", "id": 432044}, {"name": "فرهنگ_و_مستندات_نرم‌افزار_آزاد", "id": 432049}, {"name": "نرم‌افزارهای_دارای_اجازه‌نامه_ام‌آی‌تی", "id": 433656}, {"name": "بیت‌کوین", "id": 2090373}, {"name": "نرم‌افزارهای_آزاد_منحصر_به_ویندوز", "id": 2464340}, {"name": "نرم‌افزارهای_سیستمی_آزاد", "id": 2464342}, {"name": "شرکت‌های_مرتبط_با_نرم‌افزار_آزاد", "id": 2464343}, {"name": "نرم‌افزارهای_دارای_پروانه_ال‌جی‌پی‌ال", "id": 2467545}, {"name": "اجازه‌نامه‌های_نرم‌افزاری_آزاد_و_متن‌باز", "id": 2509095}, {"name": "نرم‌افزارهایی_که_از_پروانه_جی‌پی‌ال_استفاده_می‌کنند", "id": 2527355}, {"name": "نرم‌افزارهایی_که_از_پروانه_آپاچی_استفاده_می‌کنند", "id": 2527364}, {"name": "نرم‌افزار_آزاد", "id": 15585}, {"name": "برنامه‌نویسان_نرم‌افزار_آزاد", "id": 432995}, {"name": "نرم‌افزارهای_علمی_آزاد", "id": 1559412}, {"name": "نرم‌افزارهای_آموزشی_آزاد", "id": 2490780}, {"name": "بازی‌های_ویدئویی_متن‌باز", "id": 2505133}, {"name": "ویرایشگرهای_متن_آزاد", "id": 518031}, {"name": "لینوکس_موبایل", "id": 527209}, {"name": "اندروید", "id": 2127016}, {"name": "کامپایلرها_و_مفسرهای_آزاد", "id": 441787}, {"name": "محیط‌های_توسعه_مجتمع_آزاد", "id": 448453}, {"name": "کتابخانه‌های_رایانه‌ای_آزاد", "id": 2390852}, {"name": "نرم‌افزارهایی_که_از_پروانه_بی‌اس‌دی_استفاده_می‌کنند", "id": 2800285}, {"name": "نرم‌افزارهایی_که_از_پروانه_عمومی_همگانی_آفرو_استفاده_می‌کنند", "id": 3687429}]}