{"name": "تاریخ_نیویورک_سیتی", "id": 1803430, "predecessors": [{"name": "نیویورک_سیتی", "id": 2570541}, {"name": "تاریخ_شهرهای_ایالات_متحده_آمریکا", "id": 758503}, {"name": "آمارگیری‌های_نفوس_ایالات_متحده_آمریکا", "id": 2663764}], "successors": [{"name": "حملات_۱۱_سپتامبر", "id": 806312}, {"name": "رویدادها_در_نیویورک", "id": 1508238}, {"name": "زمین‌چهره‌های_تاریخی_ملی_در_نیویورک_سیتی", "id": 2294299}, {"name": "شرکت‌های_پیشین_فهرست_شده_در_بورس_نیویورک", "id": 2477232}, {"name": "شرکت‌های_منحل‌شده_نیویورک_سیتی", "id": 4541645}, {"name": "ساختمان‌ها_و_سازه‌های_ثبت_ملی_شده_در_حال_ساخت_در_منهتن", "id": 2295062}, {"name": "افراد_مرتبط_با_کارخانه", "id": 5475267}]}