{"name": "گیاگان_استرالیا", "id": 1812157, "predecessors": [{"name": "جغرافیای_سیاسی", "id": 99429}, {"name": "گیاه‌شناسی", "id": 27114}], "successors": [{"name": "گونه‌های_گیاهی_مهاجم_در_استرالیا", "id": 1546978}, {"name": "گیاهان_بومی_استرالیا", "id": 1638369}, {"name": "گیاهان_باغی_استرالیا", "id": 1812418}, {"name": "درختان_استرالیا", "id": 1823898}, {"name": "گیاهان_گوشت‌خوار_استرالیا", "id": 3395151}, {"name": "کاجیان_استرالیا", "id": 1817810}, {"name": "دولپه‌ای‌های_نو_استرالیای_غربی", "id": 1811717}, {"name": "چنارسانان_استرالیا", "id": 1816895}, {"name": "میخک‌سانان_استرالیا", "id": 2091656}, {"name": "راسته_نخودیان_استرالیا", "id": 1811773}, {"name": "رزیدهای_استرالیای_غربی", "id": 1815018}, {"name": "موردسانان_استرالیا", "id": 2092664}]}