{"name": "رفتارهای_انسان", "id": 184365, "predecessors": [{"name": "انسان‌ها", "id": 265394}, {"name": "رفتار", "id": 420695}, {"name": "روان‌شناسی", "id": 153701}, {"name": "درون‌مایه", "id": 266239}], "successors": [{"name": "عادت‌ها", "id": 24008}, {"name": "روان‌شناسی", "id": 153701}, {"name": "خشونت", "id": 184364}, {"name": "مناسک_دین", "id": 203085}, {"name": "همجنس‌گرایی", "id": 234764}, {"name": "خلاقیت", "id": 243487}, {"name": "خودپروری", "id": 265334}, {"name": "زندگی_شخصی", "id": 265335}, {"name": "تبعیض", "id": 305953}, {"name": "نسبت‌های_خانوادگی", "id": 307508}, {"name": "آیین‌ها", "id": 315350}, {"name": "میل_جنسی_در_انسان", "id": 341969}, {"name": "هیجان", "id": 352174}, {"name": "اختلال_شخصیت", "id": 397787}, {"name": "فلسفه_اخلاق", "id": 411264}, {"name": "فریب‌کاری", "id": 443573}, {"name": "روابط_میان‌فردی", "id": 502664}, {"name": "همکاری", "id": 502686}, {"name": "معنویت", "id": 624508}, {"name": "خودشیفتگی", "id": 885430}, {"name": "شخصیت", "id": 885434}, {"name": "رفتار_سازمانی", "id": 923152}, {"name": "آداب", "id": 966441}, {"name": "رفتارشناسی_مشتریان", "id": 1001963}, {"name": "فرایندهای_گروهی", "id": 1720526}, {"name": "پوزیشن‌های_انسان", "id": 1801183}, {"name": "ساختارگرایی_اجتماعی", "id": 2117163}, {"name": "امور_مالی_رفتاری", "id": 3701045}, {"name": "فرزندپروری", "id": 5302492}, {"name": "ورزش", "id": 10898}, {"name": "سرگرمی", "id": 204715}, {"name": "مسافرت", "id": 517425}, {"name": "سرگرمی‌ها", "id": 37939}, {"name": "بازی‌ها", "id": 237395}, {"name": "تمرین‌های_بدنی", "id": 356877}, {"name": "بازی‌کردن", "id": 412587}, {"name": "فرهنگ_آشامیدن", "id": 716851}, {"name": "ماساژ", "id": 1778303}, {"name": "فیلم‌های_با_محتوای_رقص", "id": 480791}, {"name": "جنگ‌ها", "id": 63244}, {"name": "ناکامی‌های_مهندسی", "id": 323296}, {"name": "سلاح‌های_کشتار_جمعی", "id": 1502883}, {"name": "مواد_منفجره", "id": 294579}, {"name": "انفجارها_در_ایران", "id": 1512751}, {"name": "نسل‌کشی", "id": 155158}, {"name": "کشتار_جمعی_در_ادبیات_داستانی", "id": 1821432}, {"name": "تیراندازی‌های_جمعی", "id": 3688843}, {"name": "یادگیری", "id": 266299}, {"name": "انگیزه", "id": 859563}, {"name": "نفوذ_(اجتماعی_و_سیاسی)", "id": 4315495}, {"name": "کشتار_جمعی_در_۱۹۴۱_(میلادی)", "id": 1547533}, {"name": "کشتار_جمعی_در_۲۰۱۵_(میلادی)", "id": 3381883}, {"name": "کشتار_جمعی_در_۲۰۱۶_(میلادی)", "id": 3578013}, {"name": "کشتار_جمعی_در_۲۰۱۷_(میلادی)", "id": 3818591}, {"name": "کشتار_جمعی_در_۲۰۱۸_(میلادی)", "id": 4365136}, {"name": "کشتار_جمعی_در_۲۰۱۹_(میلادی)", "id": 4841771}, {"name": "حملات_۱۱_سپتامبر", "id": 806312}, {"name": "نسل‌کشی_رواندا", "id": 1322396}, {"name": "نسل‌کشی‌ها", "id": 4261067}, {"name": "درگیری‌های_سده_۱۷_(میلادی)", "id": 540353}, {"name": "درگیری‌های_سده_۲۱_(میلادی)", "id": 962201}, {"name": "درگیری‌های_سده_۱۶_(میلادی)", "id": 1515460}, {"name": "درگیری‌های_سده_۲۰_(میلادی)", "id": 1674717}, {"name": "درگیری‌های_سده_۱۹_(میلادی)", "id": 1674722}, {"name": "درگیری‌های_سده_۱۳_(میلادی)", "id": 2132118}, {"name": "درگیری‌های_سده_۷_(میلادی)", "id": 2132125}, {"name": "درگیری‌های_سده_۶_(پیش_از_میلاد)", "id": 2132585}, {"name": "درگیری‌های_سده_۴_(میلادی)", "id": 3603955}]}