{"name": "کانی‌ها", "id": 218320, "predecessors": [{"name": "بلورها", "id": 1488618}, {"name": "ترکیب‌های_شیمیایی", "id": 290665}, {"name": "منابع_طبیعی", "id": 2451708}, {"name": "مواد_طبیعی", "id": 237577}, {"name": "کانی‌شناسی", "id": 15359}, {"name": "بلورشناسی", "id": 118008}], "successors": [{"name": "گوهرسنگ‌ها", "id": 261697}, {"name": "کانی‌های_آهن", "id": 311010}, {"name": "کانی‌های_آلومینیم", "id": 311014}, {"name": "کانی‌های_منیزیم", "id": 311022}, {"name": "کانی‌های_سدیم", "id": 311023}, {"name": "کانی‌های_روی", "id": 311025}, {"name": "کانی‌های_پتاسیم", "id": 311028}, {"name": "کانی‌های_کلسیم", "id": 351697}, {"name": "کانی‌های_اورانیوم", "id": 634819}, {"name": "کانی‌های_منگنز", "id": 635008}, {"name": "کانی‌های_سیلیکات", "id": 635011}, {"name": "کانی‌های_نقره", "id": 719168}, {"name": "جامدهای_بی‌شکل", "id": 742326}, {"name": "آزبست", "id": 742341}, {"name": "کانی‌های_آنتیموان", "id": 744340}, {"name": "کانی‌های_سرب", "id": 758644}, {"name": "کانی‌های_تیتانیم", "id": 758669}, {"name": "کانی‌های_رمبوئدریک", "id": 805342}, {"name": "منابع_طبیعی", "id": 2451708}, {"name": "کانی‌های_تابناک", "id": 3674889}, {"name": "کانی‌های_صنعتی", "id": 4293373}, {"name": "کوارتز", "id": 311012}, {"name": "کانی‌های_سولفید", "id": 311011}, {"name": "کانی‌های_سولفات", "id": 311026}, {"name": "کانی‌های_فسفات", "id": 311090}, {"name": "کانی‌های_اکسید", "id": 634108}, {"name": "کانی‌های_هالید", "id": 634825}, {"name": "کانی‌های_کربنات", "id": 642843}, {"name": "کانی‌های_عناصر_آزاد", "id": 742805}, {"name": "کانی‌های_سولفور", "id": 805326}, {"name": "کانی‌های_بورات", "id": 1047577}, {"name": "زئولیت‌ها", "id": 867582}, {"name": "تبخیری‌ها", "id": 2090536}, {"name": "کانی‌های_مس", "id": 311009}]}