{"name": "نرم‌افزار_ارتباطی", "id": 2469509, "predecessors": [{"name": "نرم‌افزار", "id": 22519}, {"name": "نرم‌افزارهای_شبکه‌ای_مبتنی_بر_پروتکل_اینترنت", "id": 2491579}, {"name": "سامانه‌های_رایانه", "id": 328394}, {"name": "ارتباطات", "id": 23715}], "successors": [{"name": "مرورگرهای_وب", "id": 41404}, {"name": "نرم‌افزارهای_اجتماعی", "id": 2038892}, {"name": "ابزارهای_ارتباط_فنی", "id": 3372860}, {"name": "نرم‌افزارهای_مشارکت‌گرا", "id": 3393433}, {"name": "نرم‌افزار_مدیریت_از_راه_دور", "id": 3805812}, {"name": "مرورگرهای_وب_آزاد", "id": 425499}, {"name": "نرم‌افزارهای_آزاد_مرتبط_با_شبکه", "id": 2491806}]}