{"name": "پرندگان_آسیا", "id": 284534, "predecessors": [{"name": "پرندگان", "id": 27157}, {"name": "پرندگان_اوراسیا", "id": 1073019}, {"name": "آسیا", "id": 4518}, {"name": "جانوران", "id": 30726}], "successors": [{"name": "پرندگان_پاکستان", "id": 284533}, {"name": "پرندگان_ژاپن", "id": 410697}, {"name": "پرندگان_هند", "id": 412408}, {"name": "پرندگان_سری‌لانکا", "id": 415456}, {"name": "پرندگان_چین", "id": 415843}, {"name": "پرندگان_هنگ_کنگ", "id": 543457}, {"name": "پرندگان_تایوان", "id": 543459}, {"name": "پرندگان_افغانستان", "id": 634209}, {"name": "پرندگان_نپال", "id": 634212}, {"name": "پرندگان_قزاقستان", "id": 1003308}, {"name": "پرندگان_ارمنستان", "id": 1768645}, {"name": "پرندگان_روسیه", "id": 1768672}, {"name": "پرندگان_کره", "id": 1768723}, {"name": "پرندگان_جمهوری_آذربایجان", "id": 2391281}, {"name": "پرندگان_خاورمیانه", "id": 3388043}, {"name": "پرندگان_مهاجر_(نیم‌کره_شرقی)", "id": 3655822}, {"name": "پرندگان_شمال_آسیا", "id": 3893537}, {"name": "پرندگان_هیمالیا", "id": 3893562}, {"name": "پرندگان_مهاجر_آسیا", "id": 3893565}, {"name": "پرندگان_شبه‌جزیره_عربستان", "id": 6335530}]}