{"name": "بازی‌های_تلفن_همراه", "id": 363265, "predecessors": [{"name": "اپلیکیشن‌های_تلفن_همراه", "id": 4963391}, {"name": "نرم‌افزارهای_موبایل", "id": 634873}, {"name": "بازی‌ها", "id": 237395}], "successors": [{"name": "بازی‌های_آیفون", "id": 406812}, {"name": "بازی‌های_آی‌اواس", "id": 963355}, {"name": "بازی‌های_اندروید", "id": 2125684}, {"name": "شرکت‌های_توسعه‌دهنده_بازی‌های_تلفن_همراه", "id": 3578569}, {"name": "بازی‌های_ویندوز_فون", "id": 2312719}, {"name": "بازی‌های_بلک‌بری", "id": 3578135}, {"name": "بازی‌های_سیمبیان", "id": 3578408}]}