{"name": "شهرستان‌های_استان_افیون_قره‌حصار", "id": 3903149, "predecessors": [{"name": "شهرستان‌های_ترکیه", "id": 507895}, {"name": "استان‌های_ترکیه", "id": 4515}], "successors": [{"name": "روستاها_در_شهرستان_چای", "id": 6026487}, {"name": "روستاها_در_شهرستان_دینار", "id": 6030108}, {"name": "روستاها_در_شهرستان_احسانیه", "id": 6061675}, {"name": "روستاها_در_شهرستان_شهود", "id": 6063241}, {"name": "روستاها_در_شهرستان_سنان‌پاشا", "id": 6065217}, {"name": "روستاها_در_شهرستان_صندوق‌لی", "id": 6068667}]}