{"name": "افراد_اجتماعی_ایالات_متحده_آمریکا", "id": 3983909, "predecessors": [{"name": "اهالی_ایالات_متحده_آمریکا", "id": 1267153}, {"name": "اصطلاحات_جامعه‌شناسی", "id": 1165749}], "successors": [{"name": "خانواده_کندی", "id": 2344916}, {"name": "خانواده_کارداشیان", "id": 3251384}, {"name": "خانواده_راکفلر", "id": 1269590}, {"name": "خانواده_ترامپ", "id": 3468006}, {"name": "خانواده_شویلر", "id": 5197653}, {"name": "خانواده_لیوینگستون", "id": 5199530}, {"name": "نمودهای_فرهنگی_رونالد_ریگان", "id": 4557318}, {"name": "کارکنان_دولت_ریگان", "id": 3265334}, {"name": "اعضای_کابینه_رونالد_ریگان", "id": 3643393}, {"name": "جنگ_ویتنام", "id": 211787}, {"name": "بنجامین_فرانکلین", "id": 430558}, {"name": "آبراهام_لینکلن", "id": 236401}]}