{"name": "نویسندگان_اهل_استرالیا", "id": 400560, "predecessors": [{"name": "انسان‌ها", "id": 265394}, {"name": "ادبیات", "id": 6226}, {"name": "استرالیا", "id": 28690}, {"name": "جغرافیای_سیاسی", "id": 99429}], "successors": [{"name": "خاطره‌نویسان_اهل_استرالیا", "id": 2481177}, {"name": "فیلم‌نامه‌نویسان_اهل_استرالیا", "id": 2483609}, {"name": "رمان‌نویسان_زن_اهل_استرالیا", "id": 2482746}, {"name": "رمان‌نویسان_مرد_اهل_استرالیا", "id": 3590765}, {"name": "نویسندگان_زن_سده_۲۱_(میلادی)_اهل_استرالیا", "id": 4506023}, {"name": "نویسندگان_مرد_سده_۲۰_(میلادی)_اهل_استرالیا", "id": 4701749}, {"name": "نویسندگان_مرد_سده_۲۱_(میلادی)_اهل_استرالیا", "id": 4701756}, {"name": "رمان‌نویسان_سده_۲۱_(میلادی)_اهل_استرالیا", "id": 3612001}, {"name": "رمان‌نویسان_سده_۲۰_(میلادی)_اهل_استرالیا", "id": 3612013}, {"name": "کمدین‌های_مرد_اهل_استرالیا", "id": 4599513}, {"name": "خواننده-ترانه‌پردازان_اهل_استرالیا", "id": 4713688}]}