{"name": "ندانم‌گرایی", "id": 419047, "predecessors": [{"name": "باورها،_سنت‌ها_و_جنبش‌های_دینی", "id": 508049}, {"name": "بی‌خدایی", "id": 1786824}, {"name": "شناخت‌شناسی_دین", "id": 1758830}, {"name": "شک‌گرایی", "id": 508050}, {"name": "فلسفه_دین", "id": 317890}, {"name": "مکتب‌ها_و_سنت‌های_فلسفی", "id": 406385}, {"name": "نظریه‌های_شناخت‌شناسی", "id": 1557591}, {"name": "خدا", "id": 202188}, {"name": "جامعه‌شناسی_دین", "id": 337718}, {"name": "الهیات", "id": 317858}, {"name": "باورها", "id": 3711}], "successors": [{"name": "اندیشه_آزاد", "id": 1103058}, {"name": "بی‌خدایان_و_ندانم‌گرایان_سابق", "id": 1786839}]}