{"name": "روش‌های_بلاغت", "id": 443570, "predecessors": [{"name": "برهان‌های_فلسفی", "id": 442983}, {"name": "علوم_بلاغی", "id": 393307}, {"name": "واژگان_ادبی", "id": 420930}, {"name": "ارتباطات", "id": 23715}], "successors": [{"name": "مغالطه‌های_منطقی", "id": 442959}, {"name": "بازی_با_واژگان", "id": 1312526}, {"name": "تمثیل", "id": 1478789}, {"name": "استعاره‌ها", "id": 1511542}, {"name": "عبارت‌ها", "id": 2073581}, {"name": "عبارت‌های_انگلیسی", "id": 2430036}, {"name": "شکل‌های_سخنرانی", "id": 3704779}, {"name": "عبارت‌های_کتاب_مقدس", "id": 853685}]}