{"name": "اخلاق_اجتماعی", "id": 486648, "predecessors": [{"name": "اخلاق_کاربردی", "id": 965272}, {"name": "شاخه‌های_جامعه‌شناسی_(میان‌رشته‌ای)", "id": 266456}, {"name": "فلسفه_اجتماعی", "id": 266450}], "successors": [{"name": "موضوعات_اجتماعی", "id": 486594}, {"name": "جنسیت‌گرایی_و_جامعه", "id": 486642}, {"name": "اخلاق_زیستی", "id": 486651}, {"name": "اخلاق_تجارت", "id": 532222}, {"name": "نابرابری_اجتماعی", "id": 1775321}, {"name": "نیکوکاری", "id": 2076584}, {"name": "شیوه‌های_اعدام", "id": 1069951}, {"name": "کشتار_فراقانونی", "id": 1113681}, {"name": "فیلم‌های_درباره_اعدام", "id": 2617633}, {"name": "قانون_کار", "id": 964843}, {"name": "اقتصاد_رفاه", "id": 2091301}, {"name": "اخلاق_پزشکی", "id": 130112}, {"name": "اعدام‌شدگان_به_اتهام_بدعت_در_دین", "id": 1070032}, {"name": "زندانیان_عقیدتی_اهل_ایران", "id": 5351807}, {"name": "اخلاق_زیست‌محیطی", "id": 5859746}, {"name": "وکیل_تسخیری", "id": 5338352}]}