{"name": "حقوق_ال‌جی‌بی‌تی", "id": 505993, "predecessors": [{"name": "ال‌جی‌بی‌تی_و_جامعه", "id": 5316745}, {"name": "برابری_جنسیتی", "id": 1313198}, {"name": "حقوق_بشر", "id": 116445}, {"name": "سیاست_بر_پایه_موضوع", "id": 406402}, {"name": "گرایش‌های_جنسی_و_جامعه", "id": 810928}], "successors": [{"name": "فعالان_حقوق_همجنس‌گرایان_اهل_ایالات_متحده_آمریکا", "id": 893495}, {"name": "فعالان_حقوق_همجنس‌گرایان_در_کانادا", "id": 1880253}, {"name": "فعالان_حقوق_ال‌جی‌بی‌تی_اهل_بریتانیا", "id": 3542676}, {"name": "فعالان_حقوق_ال‌جی‌بی‌تی_اهل_فرانسه", "id": 3542680}, {"name": "ورزشکاران_ال‌جی‌بی‌تی_اهل_استرالیا", "id": 3922618}, {"name": "تاریخ_ال‌جی‌بی‌تی_در_آلمان", "id": 779507}, {"name": "فیلم‌های_بلژیکی_مرتبط_با_ال‌جی‌بی‌تی", "id": 2480049}, {"name": "افراد_ال‌جی‌بی‌تی_اهل_فرانسه", "id": 1089575}, {"name": "فیلم‌های_فرانسوی_مرتبط_با_ال‌جی‌بی‌تی", "id": 1535068}, {"name": "افراد_ال‌جی‌بی‌تی_اهل_آلمان", "id": 1089607}, {"name": "فیلم‌های_آلمانی_مرتبط_با_ال‌جی‌بی‌تی", "id": 2480043}, {"name": "افراد_ال‌جی‌بی‌تی_اهل_ژاپن", "id": 1089562}, {"name": "افراد_ال‌جی‌بی‌تی_اهل_روسیه", "id": 1089584}, {"name": "افراد_ال‌جی‌بی‌تی_اهل_اسپانیا", "id": 1089597}, {"name": "فیلم‌های_مرتبط_با_ال‌جی‌بی‌تی_اسپانیا", "id": 3215191}, {"name": "ورزشکاران_ال‌جی‌بی‌تی_اهل_هلند", "id": 3922653}, {"name": "افراد_ال‌جی‌بی‌تی_اهل_بریتانیا", "id": 1093611}, {"name": "فیلم‌های_آمریکایی_مرتبط_با_ال‌جی‌بی‌تی", "id": 1261028}, {"name": "فیلم‌های_ایتالیایی_مرتبط_با_ال‌جی‌بی‌تی", "id": 2480035}, {"name": "فیلم‌های_بریتانیایی_مرتبط_با_ال‌جی‌بی‌تی", "id": 2480048}, {"name": "فیلم‌های_ژاپنی_مرتبط_با_ال‌جی‌بی‌تی", "id": 2480053}, {"name": "فیلم‌های_کانادایی_مرتبط_با_ال‌جی‌بی‌تی", "id": 2480056}, {"name": "فیلم‌های_کره_جنوبی_مرتبط_با_ال‌جی‌بی‌تی", "id": 4617467}, {"name": "فیلم‌های_هندی_مرتبط_با_ال‌جی‌بی‌تی", "id": 4617470}, {"name": "ازدواج_همجنس_در_ایالات_متحده_آمریکا_بر_پایه_ایالت", "id": 1832686}, {"name": "سیاست‌مداران_ال‌جی‌بی‌تی_اهل_ایالات_متحده_آمریکا", "id": 4713718}, {"name": "دگرجنس‌گراسالاری_در_ایالات_متحده_آمریکا", "id": 5316748}]}