{"name": "نویسندگان_یهودی", "id": 50606, "predecessors": [{"name": "پیشه‌ها", "id": 487790}, {"name": "سازمان‌ها", "id": 90635}, {"name": "جغرافیا", "id": 36723}], "successors": [{"name": "تاریخ‌نگاران_یهودی", "id": 215853}, {"name": "خاورشناسان_یهودی", "id": 865461}, {"name": "رمان‌نویسان_یهودی", "id": 881401}, {"name": "نویسندگان_زن_یهودی", "id": 3597124}, {"name": "شاعران_یهودی", "id": 3720649}, {"name": "نمایشنامه‌نویسان_یهودی", "id": 3720683}, {"name": "نویسندگان_آمریکایی_یهودی‌تبار", "id": 181881}, {"name": "نویسندگان_یهودی_اهل_بریتانیا", "id": 2485340}, {"name": "نویسندگان_یهودی_اهل_کانادا", "id": 3256772}]}