{"name": "باورها،_سنت‌ها_و_جنبش‌های_دینی", "id": 508049, "predecessors": [{"name": "باور_و_اصول_دینی", "id": 441341}, {"name": "جنبش‌های_اجتماعی", "id": 211649}, {"name": "دین", "id": 34684}], "successors": [{"name": "بوداگرایی", "id": 9700}, {"name": "علوم_خفیه", "id": 10651}, {"name": "هندوگرایی", "id": 17531}, {"name": "مهرپرستی", "id": 46135}, {"name": "تاریخ_ادیان", "id": 66080}, {"name": "دین‌های_نوظهور", "id": 116096}, {"name": "شیطان‌پرستی", "id": 116146}, {"name": "شینتو", "id": 123438}, {"name": "دین‌های_ابراهیمی", "id": 203958}, {"name": "کنفوسیانیسم", "id": 286299}, {"name": "تائوئیسم", "id": 286972}, {"name": "ندانم‌گرایی", "id": 419047}, {"name": "خداباوری", "id": 429519}, {"name": "ادیان_توحیدی", "id": 450237}, {"name": "شک‌گرایی", "id": 508050}, {"name": "آیین_مندائی", "id": 805346}, {"name": "مزدیسنا", "id": 844374}, {"name": "دین‌های_ایرانی", "id": 1317267}, {"name": "همه‌خدایی", "id": 1322826}, {"name": "تلما", "id": 1768670}, {"name": "فلسفه_افلاطون", "id": 1997953}, {"name": "سنت‌گرایی", "id": 2091218}, {"name": "سامانه‌های_باور_دینی_بنیان‌گذاری‌شده_در_ایالات_متحده_آمریکا", "id": 6339108}, {"name": "فهرست‌های_مسلمانان", "id": 426763}, {"name": "مذاهب_اسلامی", "id": 113464}, {"name": "فرقه‌های_یهودی", "id": 498445}, {"name": "پگانیسم_ژرمنی", "id": 1540919}, {"name": "مفاهیم_فلسفی_جین", "id": 964239}, {"name": "اسلام_بر_پایه_کشور", "id": 652915}, {"name": "دین_در_ایران", "id": 1267290}, {"name": "مسیحیت_در_ایران", "id": 770418}, {"name": "مسیحیت_در_ژاپن", "id": 1513752}, {"name": "بنیادگرایی_مسیحی", "id": 4264155}, {"name": "مسیحیان_اهل_کره_جنوبی", "id": 4522396}, {"name": "مسیحیان_اهل_اندونزی", "id": 2484573}, {"name": "مسیحیان_اهل_استرالیا", "id": 2484570}, {"name": "دین_یونان_باستان", "id": 3244470}, {"name": "گروه‌های_قومی-مذهبی", "id": 5004827}, {"name": "یهودیان_اهل_بلاروس", "id": 2481787}, {"name": "یهودیان_ارتدوکس_اسرائیلی", "id": 4397623}, {"name": "سحر", "id": 865431}, {"name": "افراد_ایزدانگاشته", "id": 3464220}, {"name": "یوکای", "id": 1323384}, {"name": "مسیحیان_ارتدکس_شرقی_اهل_صربستان", "id": 3782746}, {"name": "مسیحیت", "id": 61336}, {"name": "یهودیت", "id": 88892}, {"name": "گنوستیک", "id": 507689}, {"name": "کاتولیک‌های_رومی_اهل_کره_جنوبی", "id": 4522389}, {"name": "صلح‌طلبان_مسیحی_اهل_ایالات_متحده_آمریکا", "id": 4675982}, {"name": "اسپینوزاشناسان", "id": 3515910}, {"name": "مسیحیان_ارتدکس_شرقی_اهل_لبنان", "id": 3255540}, {"name": "مسیحیان_ارتدکس_یونانی_اهل_لبنان", "id": 3760039}, {"name": "کلیسای_حواری_ارمنی", "id": 3195463}, {"name": "مسیحیان_ارتودوکس_روسیه", "id": 805113}, {"name": "مارونی‌های_اهل_لبنان", "id": 2484185}]}