{"name": "تصاویر_درخواستی_در_ویکی‌پدیا", "id": 5103354, "predecessors": [{"name": "مدیریت_ویکی‌پدیا", "id": 49566}], "successors": [{"name": "مقاله‌های_سال‌ها_نیازمند_تصویر", "id": 855744}, {"name": "مقاله‌های_منظومه_شمسی_نیازمند_تصویر", "id": 855748}, {"name": "مقاله‌های_فوتبال_نیازمند_تصویر", "id": 907159}, {"name": "مقاله‌های_شهرها_نیازمند_تصویر", "id": 907160}, {"name": "مقاله‌های_روسیه_نیازمند_تصویر", "id": 907161}, {"name": "مقاله‌های_ژاپن_نیازمند_تصویر", "id": 907162}, {"name": "مقاله‌های_فلسفه_نیازمند_تصویر", "id": 907163}, {"name": "مقاله‌های_فیزیک_نیازمند_تصویر", "id": 907164}, {"name": "مقاله‌های_ایالات_متحده_آمریکا_نیازمند_تصویر", "id": 907165}, {"name": "مقاله‌های_اسلام_نیازمند_تصویر", "id": 907166}, {"name": "مقاله‌های_سیاست_نیازمند_تصویر", "id": 907168}, {"name": "مقاله‌های_گیاهان_نیازمند_تصویر", "id": 907169}, {"name": "مقاله‌های_داروشناسی_نیازمند_تصویر", "id": 907170}, {"name": "مقاله‌های_مسیحیت_نیازمند_تصویر", "id": 907171}, {"name": "مقاله‌های_زمین‌شناسی_نیازمند_تصویر", "id": 907172}, {"name": "مقاله‌های_افغانستان_نیازمند_تصویر", "id": 907173}, {"name": "مقاله‌های_سنگ‌ها_و_مواد_معدنی_نیازمند_تصویر", "id": 907175}, {"name": "مقاله‌های_تلویزیون_نیازمند_تصویر", "id": 907176}, {"name": "مقاله‌های_کره_نیازمند_تصویر", "id": 907177}, {"name": "مقاله‌های_ایتالیا_نیازمند_تصویر", "id": 907178}, {"name": "مقاله‌های_مخابرات_نیازمند_تصویر", "id": 907179}, {"name": "مقاله‌های_ترکیه_نیازمند_تصویر", "id": 907180}, {"name": "مقاله‌های_مواد_شیمیایی_نیازمند_تصویر", "id": 907181}, {"name": "مقاله‌های_دانشگاه‌ها_نیازمند_تصویر", "id": 907182}, {"name": "مقاله‌های_خودروها_نیازمند_تصویر", "id": 907183}, {"name": "مقاله‌های_دین_نیازمند_تصویر", "id": 907184}, {"name": "مقاله‌های_زبان‌ها_نیازمند_تصویر", "id": 907185}, {"name": "مقاله‌های_امامزاده_نیازمند_تصویر", "id": 911186}, {"name": "مقاله‌های_اسرائیل_نیازمند_تصویر", "id": 915302}, {"name": "مقاله‌های_استرالیا_نیازمند_تصویر", "id": 915303}, {"name": "مقاله‌های_سوسیالیسم_نیازمند_تصویر", "id": 915304}, {"name": "مقاله‌های_علوم_رایانه_نیازمند_تصویر", "id": 915308}, {"name": "مقاله‌های_ماهی‌ها_نیازمند_تصویر", "id": 915313}, {"name": "مقاله‌های_کالبدشناسی_نیازمند_تصویر", "id": 915315}, {"name": "مقاله‌های_میراث_جهانی_یونسکو_نیازمند_تصویر", "id": 915316}, {"name": "مقاله‌های_فنلاند_نیازمند_تصویر", "id": 915317}, {"name": "مقاله‌های_پرتغال_نیازمند_تصویر", "id": 915319}, {"name": "مقاله‌های_فلسطین_نیازمند_تصویر", "id": 915320}, {"name": "مقاله‌های_فناوری_نیازمند_تصویر", "id": 915321}, {"name": "مقاله‌های_سوریه_نیازمند_تصویر", "id": 915322}, {"name": "مقاله‌های_اینترنت_نیازمند_تصویر", "id": 915323}, {"name": "مقاله‌های_خط‌ها_نیازمند_تصویر", "id": 915324}, {"name": "مقاله‌های_شعر_نیازمند_تصویر", "id": 915325}, {"name": "مقاله‌های_کتاب_مقدس_نیازمند_تصویر", "id": 915326}, {"name": "مقاله‌های_پستانداران_نیازمند_تصویر", "id": 915327}, {"name": "مقاله‌های_آموزش_و_پرورش_نیازمند_تصویر", "id": 915328}, {"name": "مقاله‌های_ادبیات_نیازمند_تصویر", "id": 915330}, {"name": "مقاله‌های_کارائیب_نیازمند_تصویر", "id": 915331}, {"name": "مقاله‌های_مکزیک_نیازمند_تصویر", "id": 915333}, {"name": "مقاله‌های_لهستان_نیازمند_تصویر", "id": 915334}, {"name": "مقاله‌های_امنیت_رایانه‌ای_نیازمند_تصویر", "id": 915341}, {"name": "مقاله‌های_لبنان_نیازمند_تصویر", "id": 915342}, {"name": "مقاله‌های_مزدیسنا_نیازمند_تصویر", "id": 915343}, {"name": "مقاله‌های_نرم‌افزار_نیازمند_تصویر", "id": 915346}, {"name": "مقاله‌های_هندوئیسم_نیازمند_تصویر", "id": 915347}, {"name": "مقاله‌های_لینوکس_نیازمند_تصویر", "id": 915349}, {"name": "مقاله‌های_کتابخانه‌ها_نیازمند_تصویر", "id": 915351}, {"name": "مقاله‌های_زیست‌شناسی_نیازمند_تصویر", "id": 915352}, {"name": "مقاله‌های_ویتنام_نیازمند_تصویر", "id": 915353}, {"name": "مقاله‌های_مالزی_نیازمند_تصویر", "id": 915354}, {"name": "مقاله‌های_رودها_نیازمند_تصویر", "id": 915355}, {"name": "مقاله‌های_تاجیکستان_نیازمند_تصویر", "id": 915356}, {"name": "مقاله‌های_شطرنج_نیازمند_تصویر", "id": 915357}, {"name": "مقاله‌های_نروژ_نیازمند_تصویر", "id": 915358}, {"name": "مقاله‌های_مصر_باستان_نیازمند_تصویر", "id": 915361}, {"name": "مقاله‌های_نخستی‌ها_نیازمند_تصویر", "id": 915362}, {"name": "مقاله‌های_بریتانیا_نیازمند_تصویر", "id": 915363}, {"name": "مقاله‌های_کشتی_حرفه‌ای_نیازمند_تصویر", "id": 915364}, {"name": "مقاله‌های_نیوزیلند_نیازمند_تصویر", "id": 915365}, {"name": "مقاله‌های_سرزمین_میانی_نیازمند_تصویر", "id": 915366}, {"name": "مقاله‌های_مایکروسافت_نیازمند_تصویر", "id": 915368}, {"name": "مقاله‌های_مراکش_نیازمند_تصویر", "id": 915369}, {"name": "مقاله‌های_جوندگان_نیازمند_تصویر", "id": 915370}, {"name": "مقاله‌های_جزیره‌ها_نیازمند_تصویر", "id": 915372}, {"name": "مقاله‌های_اردن_نیازمند_تصویر", "id": 915374}, {"name": "مقاله‌های_آفریقای_جنوبی_نیازمند_تصویر", "id": 915375}, {"name": "مقاله‌های_اروپا_نیازمند_تصویر", "id": 915376}, {"name": "مقاله‌های_دندان‌پزشکی_نیازمند_تصویر", "id": 915377}, {"name": "مقاله‌های_معنویت_نیازمند_تصویر", "id": 915379}, {"name": "مقاله‌های_شمالگان_نیازمند_تصویر", "id": 915381}, {"name": "مقاله‌های_جنگ‌افزارهای_گرم_نیازمند_تصویر", "id": 915382}, {"name": "مقاله‌های_گربه‌ها_نیازمند_تصویر", "id": 915383}, {"name": "مقاله‌های_مونته‌نگرو_نیازمند_تصویر", "id": 915384}, {"name": "مقاله‌های_اتیوپی_نیازمند_تصویر", "id": 915385}, {"name": "مقاله‌های_بسکتبال_نیازمند_تصویر", "id": 915386}, {"name": "مقاله‌های_هری_پاتر_نیازمند_تصویر", "id": 915387}, {"name": "مقاله‌های_آمریکای_جنوبی_نیازمند_تصویر", "id": 915388}, {"name": "مقاله‌های_سگ‌ها_نیازمند_تصویر", "id": 915389}, {"name": "مقاله‌های_امارات_متحده_عربی_نیازمند_تصویر", "id": 915390}, {"name": "مقاله‌های_دانمارک_نیازمند_تصویر", "id": 915391}, {"name": "مقاله‌های_میکروبیولوژی_نیازمند_تصویر", "id": 915392}, {"name": "مقاله‌های_قطر_نیازمند_تصویر", "id": 915393}, {"name": "مقاله‌های_بهائیت_نیازمند_تصویر", "id": 915394}, {"name": "مقاله‌های_ماه_نیازمند_تصویر", "id": 915395}, {"name": "مقاله‌های_تایلند_نیازمند_تصویر", "id": 915397}, {"name": "مقاله‌های_استونی_نیازمند_تصویر", "id": 915398}, {"name": "مقاله‌های_هنگ_کنگ_نیازمند_تصویر", "id": 915401}, {"name": "مقاله‌های_تاریخ_اروپا_نیازمند_تصویر", "id": 915406}, {"name": "مقاله‌های_لیتوانی_نیازمند_تصویر", "id": 915409}, {"name": "مقاله‌های_تاریخ_ایالات_متحده_آمریکا_نیازمند_تصویر", "id": 915410}, {"name": "مقاله‌های_کامبوج_نیازمند_تصویر", "id": 915422}, {"name": "مقاله‌های_ایرلند_شمالی_نیازمند_تصویر", "id": 915430}, {"name": "مقاله‌های_عکاسی_نیازمند_تصویر", "id": 2211047}, {"name": "مقاله‌های_یمن_نیازمند_تصویر", "id": 2211048}, {"name": "مقاله‌های_طبرستان_نیازمند_تصویر", "id": 2211051}, {"name": "مقاله‌های_اخترشناسی_نیازمند_تصویر", "id": 3370545}, {"name": "مقاله‌های_جامعه‌شناسی_نیازمند_تصویر", "id": 3573011}, {"name": "مقاله‌های_انسان‌شناسی_نیازمند_تصویر", "id": 3822784}]}