{"name": "فیلم‌های_درام_زندگی‌نامه‌ای_دهه_۲۰۰۰_(میلادی)", "id": 5140856, "predecessors": [{"name": "فیلم‌های_زندگی‌نامه‌ای_دهه_۲۰۰۰_(میلادی)", "id": 3611842}, {"name": "فیلم‌های_زندگی‌نامه‌ای", "id": 28666}, {"name": "سده_۲۱_(میلادی)", "id": 406428}], "successors": [{"name": "فیلم‌های_درام_زندگی‌نامه‌ای_۲۰۰۶_(میلادی)", "id": 6222870}, {"name": "فیلم‌های_درام_زندگی‌نامه‌ای_۲۰۰۷_(میلادی)", "id": 6225658}, {"name": "فیلم‌های_درام_زندگی‌نامه‌ای_۲۰۰۸_(میلادی)", "id": 6226591}, {"name": "فیلم‌های_درام_زندگی‌نامه‌ای_۲۰۰۹_(میلادی)", "id": 6227964}]}