{"name": "مدیریت", "id": 54893, "predecessors": [{"name": "رهبری", "id": 494798}, {"name": "علوم_کاربردی", "id": 41366}, {"name": "کسب_و_کار", "id": 210624}, {"name": "بازرگانی", "id": 242479}, {"name": "دموکراسی", "id": 1095383}, {"name": "رشته‌های_آکادمیک", "id": 9443}], "successors": [{"name": "سازمان‌ها", "id": 90635}, {"name": "مدیریت_ریسک", "id": 91648}, {"name": "مدیریت_فناوری_اطلاعات", "id": 151679}, {"name": "کیفیت", "id": 218318}, {"name": "برنامه‌ریزی", "id": 299291}, {"name": "مدیریت_پروژه", "id": 299297}, {"name": "مدیریت_کیفیت", "id": 304163}, {"name": "مدیریت_منابع_انسانی", "id": 344399}, {"name": "حکومت", "id": 406389}, {"name": "مدیریت_بازرگانی", "id": 427379}, {"name": "برون‌سپاری", "id": 436071}, {"name": "مدیریت_شرایط_اضطراری", "id": 438535}, {"name": "رهبری", "id": 494798}, {"name": "مدیریت_پسماند", "id": 500736}, {"name": "استخدام", "id": 507416}, {"name": "مقاله‌های_خرد_مدیریت", "id": 520836}, {"name": "مدیریت_زنجیره_تأمین", "id": 533252}, {"name": "شغل‌های_مدیریت", "id": 1085796}, {"name": "حاکمیت_بنگاه", "id": 1316190}, {"name": "مدیریت_بر_پایه_نوع", "id": 1489588}, {"name": "مدیریت_فرایند", "id": 1720683}, {"name": "حسابداری_مدیریت", "id": 1776685}, {"name": "اندیشه_نظام‌ها", "id": 2697009}, {"name": "نظریه_مدیریت", "id": 3700760}, {"name": "تابلوهای_راهنمایی_و_رانندگی", "id": 1103540}, {"name": "تجهیزات_خیابانی", "id": 1272694}, {"name": "مدیریت_ترافیک_جاده", "id": 1598056}, {"name": "کارآفرینی", "id": 90328}, {"name": "کارآفرینان", "id": 359637}, {"name": "آمادگی_برای_فاجعه", "id": 532813}, {"name": "ایمنی_و_بهداشت_شغلی", "id": 917932}]}