{"name": "تاریخ_زمین‌شناختی_زمین", "id": 793570, "predecessors": [{"name": "زمین‌شناسی", "id": 6096}, {"name": "زمین‌شناسی_تاریخی", "id": 295383}], "successors": [{"name": "دوران‌های_زمین‌شناسی", "id": 112395}, {"name": "جنگل‌ها", "id": 248719}, {"name": "زمین‌ساخت_صفحه‌ای", "id": 793571}, {"name": "چینه‌شناسی", "id": 865171}, {"name": "زمین‌گاه‌شناسی", "id": 867543}, {"name": "دیرین‌اقلیم‌شناسی", "id": 1131128}, {"name": "جانوران_بزرگ", "id": 1485112}, {"name": "ژئومورفولوژی", "id": 2043390}, {"name": "رویدادهای_انقراض", "id": 2100552}, {"name": "دوره‌های_زمین‌شناسی", "id": 3460713}, {"name": "زمین‌شناسی_تاریخی", "id": 295383}, {"name": "قاره_آمریکا", "id": 25891}, {"name": "اوراسیا", "id": 911007}, {"name": "دادگان_برخوردهای_زمین", "id": 2412951}, {"name": "فیلم‌های_واقع‌شده_در_اقیانوسیه", "id": 1166436}, {"name": "بازی‌های_ویدئویی_واقع‌شده_در_اقیانوسیه", "id": 2290544}, {"name": "فیلم‌های_واقع‌شده_در_هاوایی", "id": 3221934}, {"name": "فیلم‌های_واقع‌شده_در_نیوزیلند", "id": 1167059}, {"name": "دورهای_زمین‌شناسی", "id": 3456948}, {"name": "عصرهای_زمین‌شناسی", "id": 3460716}, {"name": "پیشین‌زیستی", "id": 881683}, {"name": "جانداران_پدیدآمده_در_کربنیفر", "id": 3497106}, {"name": "جانداران_موجود_پدیدآمده_در_کرتاسه", "id": 5284496}, {"name": "انقراض‌های_تریاس_پسین", "id": 3505025}, {"name": "دایناسورهای_تریاس_پسین", "id": 3612898}, {"name": "جانداران_موجود_پدیدآمده_در_ژوراسیک", "id": 3686896}, {"name": "جانداران_موجود_پدیدآمده_در_ژوراسیک_پیشین", "id": 5276909}, {"name": "جانداران_موجود_پدیدآمده_در_ژوراسیک_پسین", "id": 5301846}, {"name": "آبشارهای_نیوزیلند", "id": 1102917}, {"name": "میراث_جهانی_یونسکو_در_استرالیا", "id": 169201}, {"name": "فهرست_میراث_ملی_استرالیا", "id": 3966488}, {"name": "آبشارهای_کوئینزلند", "id": 945632}, {"name": "سواحل_نیو_ساوت_ولز", "id": 3966485}, {"name": "کارآفرینان_اهل_استرالیا", "id": 2483761}, {"name": "جانداران_موجود_پدیدآمده_در_تریاس", "id": 3686893}, {"name": "خزندگان_تریاس_میانه_اروپا", "id": 5286726}, {"name": "خزندگان_تریاس_پسین_اروپا", "id": 5298072}, {"name": "دایناسورهای_ژوراسیک_پسین_آمریکای_شمالی", "id": 5504817}]}