{"name": "ادبیات_قرون_وسطی", "id": 852547, "predecessors": [{"name": "تاریخ_ادبیات", "id": 628043}, {"name": "تاریخ_فرهنگ", "id": 2478220}, {"name": "ادبیات", "id": 6226}, {"name": "داستان‌های_تاریخی", "id": 1317506}, {"name": "فرهنگ", "id": 114865}], "successors": [{"name": "نویسندگان_سده_۱۱_(میلادی)", "id": 2133397}, {"name": "نویسندگان_سده_۱۳_(میلادی)", "id": 2133398}, {"name": "شاعران_قرون_وسطی", "id": 3373067}, {"name": "نویسندگان_ادبیات_فارسی_دوران_قرون_وسطی", "id": 3518321}, {"name": "کتاب‌های_سده_۱۰_(میلادی)", "id": 2639951}, {"name": "کتاب‌های_سده_۱۳_(میلادی)", "id": 3247093}, {"name": "کتاب‌های_سده_۱۲_(میلادی)", "id": 3247097}, {"name": "شعرهای_سده_۱۴_(میلادی)", "id": 3683861}, {"name": "حدیث", "id": 221972}, {"name": "کتاب‌های_عربی_سده_۹_(میلادی)", "id": 4531829}, {"name": "فیلسوفان_عرب‌زبان", "id": 503641}, {"name": "فیلسوفان_سده_۱۲_(میلادی)", "id": 1668954}, {"name": "فیلسوفان_فارسی‌زبان_قرون_وسطی", "id": 3965837}, {"name": "نویسندگان_سده_۱۵_(میلادی)_اهل_فرانسه", "id": 1646772}, {"name": "نویسندگان_عربی_سده_۱۵_(میلادی)", "id": 3797085}, {"name": "ادبیات_عربی_قرون_وسطی", "id": 4937369}, {"name": "تاریخ‌نگاران_اهل_امپراتوری_روم_شرقی", "id": 616684}, {"name": "نویسندگان_سده_۱۲_(میلادی)_اهل_فرانسه", "id": 1646759}, {"name": "نویسندگان_لاتین_سده_۱۲_(میلادی)", "id": 2133416}, {"name": "نویسندگان_عربی_سده_۱۲_(میلادی)", "id": 3797043}, {"name": "نویسندگان_سده_۱۴_(میلادی)_اهل_فرانسه", "id": 1646791}, {"name": "نویسندگان_لاتین_سده_۱۴_(میلادی)", "id": 2133427}, {"name": "نویسندگان_عربی_سده_۱۴_(میلادی)", "id": 3796662}, {"name": "نویسندگان_عربی_سده_۱۰_(میلادی)", "id": 3796669}, {"name": "نویسندگان_لاتین_سده_۶_(میلادی)", "id": 4581704}, {"name": "شاعران_عربی_سده_۷_(میلادی)", "id": 3800625}, {"name": "نویسندگان_عربی_سده_۸_(میلادی)", "id": 3797035}, {"name": "نویسندگان_سده_۵_(میلادی)_اهل_امپراتوری_روم_شرقی", "id": 4581539}, {"name": "افسانه‌های_قرون_وسطی", "id": 1260998}, {"name": "تاریخ_سنتی_بریتانیا", "id": 4285916}, {"name": "ادبیات_جنگ‌های_صلیبی", "id": 4981530}]}