{"name": "کنشگران_ضدجنگ_اهل_ایالات_متحده_آمریکا", "id": 886474, "predecessors": [{"name": "فعالان_اجتماعی_اهل_ایالات_متحده_آمریکا", "id": 2583230}, {"name": "انسان‌ها", "id": 265394}], "successors": [{"name": "کنشگران_مخالف_جنگ_عراق_اهل_ایالات_متحده_آمریکا", "id": 2349361}, {"name": "مخالفان_سربازی_اهل_ایالات_متحده_آمریکا", "id": 2484313}, {"name": "صلح‌طلبان_ایالات_متحده_آمریکا", "id": 3215035}, {"name": "کنشگران_مخالف_جنگ_ویتنام_اهل_ایالات_متحده_آمریکا", "id": 3606042}, {"name": "کنشگران_مخالف_جنگ‌افزارهای_هسته‌ای_اهل_ایالات_متحده_آمریکا", "id": 4693429}]}