{"name": "سازمان‌ها", "id": 90635, "predecessors": [{"name": "جامعه", "id": 112945}, {"name": "جامعه‌شناسی", "id": 18166}, {"name": "سامانه‌های_اجتماعی", "id": 263436}, {"name": "مدیریت", "id": 54893}, {"name": "سامانه‌ها", "id": 37161}], "successors": [{"name": "سازمان‌های_مردم‌نهاد", "id": 216831}, {"name": "سازمان‌های_تخیلی", "id": 368400}, {"name": "انواع_سازمان", "id": 405692}, {"name": "سازمان‌های_ناسودبر", "id": 440111}, {"name": "سازمان‌های_برنده_جایزه_نوبل", "id": 543182}, {"name": "فهرست_سازمان‌ها", "id": 857376}, {"name": "بنیانگذاران_سازمانی", "id": 6153579}, {"name": "اعضای_پیوسته_فرهنگستان_زبان_و_ادب_فارسی", "id": 433604}, {"name": "سازمان‌های_میان‌دولتی_بنیان‌گذاری‌شده_بر_پایه_معاهده", "id": 3604618}, {"name": "تشکل‌های_دانشجویی", "id": 194841}, {"name": "سازمان‌های_کرد", "id": 253835}, {"name": "ابرسازمان‌ها", "id": 1254965}, {"name": "اتحادیه‌های_صنفی", "id": 417763}, {"name": "سازمان‌های_بین‌المللی", "id": 6258}, {"name": "اعضای_فرهنگستان_ایران", "id": 2437446}, {"name": "انجمن‌های_تخصصی_ایالات_متحده_آمریکا", "id": 2101833}, {"name": "شرکت‌های_عضو_یاتا", "id": 857406}, {"name": "اعضای_منسا", "id": 4247225}, {"name": "اعضای_اتحادیه_پخش_برنامه‌های_اروپایی", "id": 5523725}, {"name": "دولت_در_ادبیات_داستانی", "id": 2051802}, {"name": "سازمان‌های_اسلامی", "id": 860808}, {"name": "جنبش_بهکتی", "id": 1315777}, {"name": "جلسات", "id": 804845}, {"name": "اعضای_آکادمی_سلطنتی", "id": 3820400}, {"name": "اعضای_آکادمی_هنرهای_زیبا", "id": 3822525}, {"name": "پیشاهنگی_عقاب", "id": 3722899}, {"name": "تیم‌های_ان‌بی‌ای", "id": 259640}, {"name": "تیم‌های_لیگ_برتر_فوتبال_آمریکا", "id": 2780445}, {"name": "تیم‌های_لیگ_ملی_فوتبال", "id": 853939}, {"name": "بازیکنان_اوکلند_ریدرز", "id": 5490700}, {"name": "بازیکنان_باشگاه_سن‌فرانسیسکو_۴۹رز", "id": 4711210}, {"name": "سازمان‌های_واشینگتن،_دی.سی.", "id": 2077312}, {"name": "شرکت‌های_ملبورن", "id": 1499561}, {"name": "شرکت‌های_سیدنی", "id": 1511976}, {"name": "شرکت‌های_بریزبن", "id": 2295893}, {"name": "شرکت‌های_پرت", "id": 2295909}, {"name": "گالری‌ها_و_موزه‌های_هنر_در_نیویورک", "id": 6202215}, {"name": "بازیکنان_باشگاه_نیوکاسل_یونایتد_جتس", "id": 3705967}, {"name": "بازیکنان_باشگاه_سنترال_کوئست_مارینرز", "id": 3705963}, {"name": "بازیکنان_باشگاه_آدلاید_یونایتد", "id": 3664531}, {"name": "بازیکنان_باشگاه_پرث_گلوری", "id": 3664533}, {"name": "بازیکنان_باشگاه_بریزبن_رور", "id": 3705961}, {"name": "افراد_مرتبط_با_ویکی‌پدیا", "id": 2528587}, {"name": "افراد_مرتبط_با_سرن", "id": 3398798}, {"name": "یهودیان", "id": 172926}, {"name": "رهبران_مذهبی", "id": 179615}, {"name": "نویسندگان_مذهبی", "id": 1496558}, {"name": "استادان_معنوی", "id": 2507315}, {"name": "فیلسوفان_یهودی", "id": 168848}, {"name": "ورزشکاران_یهودی", "id": 179874}, {"name": "نقاشان_یهودی", "id": 226786}, {"name": "دانشمندان_یهودی", "id": 437076}, {"name": "موسیقی‌دانان_یهودی", "id": 534735}, {"name": "خاورشناسان_یهودی", "id": 865461}, {"name": "نظامیان_یهودی", "id": 2568604}, {"name": "سیاستمداران_یهودی", "id": 2717828}, {"name": "مجموعه‌داران_هنری_یهودی", "id": 3720603}, {"name": "هنرمندان_یهودی", "id": 3720604}, {"name": "طراحان_مد_یهودی", "id": 3720638}, {"name": "نیکوکاران_یهودی", "id": 3720643}, {"name": "کارکنان_مایکروسافت", "id": 804265}, {"name": "کارمندان_گوگل", "id": 856087}, {"name": "افراد_مرتبط_با_والت_دیزنی", "id": 970520}, {"name": "کارکنان_ناسا", "id": 1111945}, {"name": "افراد_اینتل", "id": 1117321}, {"name": "افراد_بی‌پی", "id": 1795565}, {"name": "افراد_جنرال_الکتریک", "id": 1828792}, {"name": "افراد_فراری", "id": 2088201}, {"name": "افراد_مرتبط_با_سان_مایکروسیستمز", "id": 2490096}, {"name": "افراد_لاکهید_مارتین", "id": 2496804}, {"name": "افراد_دوپونت", "id": 2496806}, {"name": "افراد_رویال_داچ_شل", "id": 2511992}, {"name": "افراد_گلدمن_ساکس", "id": 2557442}, {"name": "افراد_مک‌لارن", "id": 2570232}, {"name": "افراد_مریل_لینچ", "id": 2619978}, {"name": "افراد_بانک_جهانی", "id": 2620004}, {"name": "افراد_تایم", "id": 2620007}, {"name": "افراد_اچ‌پی", "id": 2620025}, {"name": "افراد_ان‌بی‌سی_یونیورسال", "id": 2620038}, {"name": "افراد_نینتندو", "id": 2620046}, {"name": "افراد_دیجیتال_اکویپمنت", "id": 2620057}, {"name": "افراد_کوکاکولا", "id": 2620059}, {"name": "افراد_استودیو_جیبلی", "id": 2620102}, {"name": "افراد_اسکوئر_انیکس", "id": 3257580}, {"name": "افراد_شرکت_ملی_مناطق_نفت‌خیز_جنوب", "id": 3542291}, {"name": "افراد_شرکت_ملی_نفت_ایران", "id": 3542292}, {"name": "افراد_در_هانا-باربرا", "id": 4074794}, {"name": "افراد_در_کمپانی_هند_شرقی_بریتانیا", "id": 4362174}, {"name": "افراد_در_مک‌کینزی_اند_کامپنی", "id": 4362177}, {"name": "مدیران_اجرایی_گلدمن_ساکس", "id": 2557436}, {"name": "بهائیان_اهل_ایران", "id": 887826}, {"name": "بهائیان_اهل_ایالات_متحده_آمریکا", "id": 887855}, {"name": "نوکیشان_بودائی", "id": 2644669}, {"name": "نوکیشان_یهودی", "id": 2644671}, {"name": "نوکیشان_مسلمان", "id": 2657499}, {"name": "نوکیشان_مسیحی", "id": 2657502}, {"name": "صلح‌طلبان_یهودی", "id": 3720693}, {"name": "افسران_کاگ‌ب", "id": 3608862}, {"name": "صلح‌طلبان_لوتری", "id": 3645278}, {"name": "پیمان‌نامه‌های_سازمان_ملل_متحد", "id": 3707084}, {"name": "رهبران_احزاب_سیاسی", "id": 3771385}, {"name": "سخنگوهای_مجلس_خلق_سوریه", "id": 2777068}, {"name": "رهبران_کارگری_اهل_ایالات_متحده_آمریکا", "id": 3675840}, {"name": "مدیران_اجرایی_اپل", "id": 795273}, {"name": "مدیران_اجرایی_بی‌بی‌سی", "id": 2637868}, {"name": "مدیران_اجرایی_دبلیودبلیوئی", "id": 5300738}, {"name": "مدیران_اجرایی_دیزنی", "id": 5856664}, {"name": "افراد_رند_کورپوریشن", "id": 5537955}, {"name": "فیلم‌های_درباره_سازمان‌های_اطلاعاتی", "id": 3723016}, {"name": "فیلم‌های_درباره_انجمن‌های_برادری_و_باشگاه‌های_زنان", "id": 3774660}, {"name": "فیلم‌های_درباره_ناسا", "id": 3775361}, {"name": "فیلم‌ها_درباره_کوکلوس‌کلان", "id": 5310350}, {"name": "فیلم‌های_گانگستری", "id": 360785}, {"name": "اعضای_فرهنگستان_علوم_پزشکی_ایران", "id": 417133}, {"name": "افراد_بلو_اسکای_استودیو", "id": 3690370}, {"name": "افراد_در_پیکسار", "id": 4362181}, {"name": "افراد_استودیوهای_پویانمایی_والت_دیزنی", "id": 4602080}, {"name": "افراد_کارتون‌های_برادران_وارنر", "id": 5015614}, {"name": "افراد_دریم‌ورکز_انیمیشن", "id": 5142494}, {"name": "هنرمندان_اس‌ام_انترتینمنت", "id": 3457589}]}