{"name": "مخترعان", "id": 99394, "predecessors": [{"name": "پیشه‌های_علوم", "id": 1772355}, {"name": "استادان_دانشگاه", "id": 152178}, {"name": "نوآوری", "id": 299296}, {"name": "اندیشه", "id": 155926}], "successors": [{"name": "راه‌یافتگان_به_تالار_مشاهیر_مخترعین_ملی", "id": 861238}, {"name": "مخترعان_خط_نوشتاری", "id": 1817942}, {"name": "زنان_مخترع", "id": 2108876}, {"name": "مخترعان_باتری", "id": 2431190}, {"name": "مخترعان_در_اسلام_قرون_وسطایی", "id": 2572661}, {"name": "پیشگامان_سینما", "id": 2627222}, {"name": "خالقان_زبان_فراساخته", "id": 3737849}, {"name": "مخترعان_تخیلی", "id": 3739930}, {"name": "مخترعان_هوانوردی", "id": 4496866}, {"name": "پیشگامان_خودروسازی", "id": 1987994}, {"name": "پیشگامان_اینترنت", "id": 2627227}, {"name": "پیشگامان_سبک‌های_موسیقی", "id": 3502873}, {"name": "پیشگامان_عکاسی", "id": 1065455}, {"name": "پیشگامان_رادیو", "id": 2627229}, {"name": "پیشگامان_تلویزیون", "id": 2627230}, {"name": "مخترعان_سده_۲۰_(میلادی)", "id": 4536777}, {"name": "تجسم‌های_فرهنگی_از_آلبرت_اینشتین", "id": 3556610}]}